desdeo_emo/EAs/BaseEA.py
desdeo_emo/EAs/BaseIndicatorEA.py
desdeo_emo/EAs/IBEA.py
desdeo_emo/EAs/IKRVEA.py
desdeo_emo/EAs/IOPIS.py
desdeo_emo/EAs/MOEAD.py
desdeo_emo/EAs/NSGAIII.py
desdeo_emo/EAs/PBEA.py
desdeo_emo/EAs/PPGA.py
desdeo_emo/EAs/RVEA.py
desdeo_emo/EAs/TournamentEA.py
desdeo_emo/EAs/__init__.py
desdeo_emo/EAs/slowRVEA.py
desdeo_emo/__init__.py
desdeo_emo/population/CreateIndividuals.py
desdeo_emo/population/Population.py
desdeo_emo/population/Population_old.py
desdeo_emo/population/SurrogatePopulation.py
desdeo_emo/population/__init__.py
desdeo_emo/problem/IOPIS.py
desdeo_emo/problem/__init__.py
desdeo_emo/recombination/BoundedPolynomialMutation.py
desdeo_emo/recombination/SimulatedBinaryCrossover.py
desdeo_emo/recombination/SinglePointCrossoverMutation.py
desdeo_emo/recombination/__init__.py
desdeo_emo/recombination/biogp_mutation.py
desdeo_emo/recombination/biogp_xover.py
desdeo_emo/recombination/evodn2_xover_mutation.py
desdeo_emo/recombination/evonn_xover_mutation.py
desdeo_emo/selection/APD_Select.py
desdeo_emo/selection/APD_Select_constraints.py
desdeo_emo/selection/IOPIS_APD.py
desdeo_emo/selection/IOPIS_NSGAIII.py
desdeo_emo/selection/MOEAD_select.py
desdeo_emo/selection/NSGAIII_select.py
desdeo_emo/selection/SelectionBase.py
desdeo_emo/selection/TournamentSelection.py
desdeo_emo/selection/__init__.py
desdeo_emo/selection/oAPD.py
desdeo_emo/selection/robust_APD.py
desdeo_emo/surrogatemodels/BioGP.py
desdeo_emo/surrogatemodels/EvoDN2.py
desdeo_emo/surrogatemodels/EvoNN.py
desdeo_emo/surrogatemodels/Problem.py
desdeo_emo/surrogatemodels/__init__.py
desdeo_emo/utilities/IsNotebook.py
desdeo_emo/utilities/ReferenceVectors.py
desdeo_emo/utilities/__init__.py
desdeo_emo/utilities/model_management.py
desdeo_emo/utilities/newRV.py
desdeo_emo/utilities/non_dominated.py
desdeo_emo/utilities/plotlyanimate.py
desdeo_emo/utilities/symmetric_vectors.py
desdeo_emo-1.5.0.dist-info/LICENSE
desdeo_emo-1.5.0.dist-info/METADATA
desdeo_emo-1.5.0.dist-info/WHEEL
desdeo_emo-1.5.0.dist-info/RECORD
