Metadata-Version: 2.1
Name: desdeo-emo
Version: 1.5.0
Summary: The python version reference vector guided evolutionary algorithm.
License: MPL-2.0
Author: Bhupinder Saini
Requires-Python: >=3.9,<3.11
Classifier: License :: OSI Approved
Classifier: Programming Language :: Python :: 3
Classifier: Programming Language :: Python :: 3.9
Classifier: Programming Language :: Python :: 3.10
Requires-Dist: desdeo-problem (>=1.5,<2.0)
Requires-Dist: plotly (>=5.10.0,<6.0.0)
Requires-Dist: pyDOE (>=0.3.8,<0.4.0)
